pgb_utils/__init__.py
pgb_utils/bigquery.py
pgb_utils/figures.py
pgb_utils/pubsub.py
pgb_utils/utils.py
pgb_utils-0.2.7.dist-info/LICENSE.txt
pgb_utils-0.2.7.dist-info/METADATA
pgb_utils-0.2.7.dist-info/WHEEL
pgb_utils-0.2.7.dist-info/top_level.txt
pgb_utils-0.2.7.dist-info/RECORD
